CHANGES.rst
CONTRIBUTORS.txt
LICENSE.txt
MANIFEST.in
Makefile
README.rst
pyproject.toml
setup.cfg
setup.py
aiohttp/__init__.py
aiohttp/_cparser.pxd
aiohttp/_find_header.h
aiohttp/_find_header.pxd
aiohttp/_helpers.pyi
aiohttp/_helpers.pyx
aiohttp/_http_parser.pyx
aiohttp/_http_writer.pyx
aiohttp/_websocket.pyx
aiohttp/abc.py
aiohttp/base_protocol.py
aiohttp/client.py
aiohttp/client_exceptions.py
aiohttp/client_proto.py
aiohttp/client_reqrep.py
aiohttp/client_ws.py
aiohttp/compression_utils.py
aiohttp/connector.py
aiohttp/cookiejar.py
aiohttp/formdata.py
aiohttp/hdrs.py
aiohttp/helpers.py
aiohttp/http.py
aiohttp/http_exceptions.py
aiohttp/http_parser.py
aiohttp/http_websocket.py
aiohttp/http_writer.py
aiohttp/locks.py
aiohttp/log.py
aiohttp/multipart.py
aiohttp/payload.py
aiohttp/py.typed
aiohttp/pytest_plugin.py
aiohttp/resolver.py
aiohttp/streams.py
aiohttp/tcp_helpers.py
aiohttp/test_utils.py
aiohttp/tracing.py
aiohttp/typedefs.py
aiohttp/web.py
aiohttp/web_app.py
aiohttp/web_exceptions.py
aiohttp/web_fileresponse.py
aiohttp/web_log.py
aiohttp/web_middlewares.py
aiohttp/web_protocol.py
aiohttp/web_request.py
aiohttp/web_response.py
aiohttp/web_routedef.py
aiohttp/web_runner.py
aiohttp/web_server.py
aiohttp/web_urldispatcher.py
aiohttp/web_ws.py
aiohttp/worker.py
aiohttp_nossl.egg-info/PKG-INFO
aiohttp_nossl.egg-info/SOURCES.txt
aiohttp_nossl.egg-info/dependency_links.txt
aiohttp_nossl.egg-info/not-zip-safe
aiohttp_nossl.egg-info/requires.txt
aiohttp_nossl.egg-info/top_level.txt
docs/Makefile
docs/abc.rst
docs/aiohttp-icon.svg
docs/aiohttp-plain.svg
docs/built_with.rst
docs/changes.rst
docs/client.rst
docs/client_advanced.rst
docs/client_quickstart.rst
docs/client_reference.rst
docs/conf.py
docs/contributing-admins.rst
docs/contributing.rst
docs/deployment.rst
docs/essays.rst
docs/external.rst
docs/faq.rst
docs/favicon.ico
docs/glossary.rst
docs/http_request_lifecycle.rst
docs/index.rst
docs/logging.rst
docs/make.bat
docs/migration_to_2xx.rst
docs/misc.rst
docs/multipart.rst
docs/multipart_reference.rst
docs/new_router.rst
docs/old-logo.png
docs/old-logo.svg
docs/powered_by.rst
docs/spelling_wordlist.txt
docs/streams.rst
docs/structures.rst
docs/testing.rst
docs/third_party.rst
