Metadata-Version: 2.1
Name: aiohttp-nossl
Version: 4.0.0a2.dev0
Summary: Async http client/server framework (asyncio)
Home-page: https://github.com/aio-libs/aiohttp
Maintainer: aiohttp team <team@aiohttp.org>
Maintainer-email: team@aiohttp.org
License: Apache 2
Project-URL: Chat: Matrix, https://matrix.to/#/#aio-libs:matrix.org
Project-URL: Chat: Matrix Space, https://matrix.to/#/#aio-libs-space:matrix.org
Project-URL: CI: GitHub Actions, https://github.com/aio-libs/aiohttp/actions?query=workflow%3ACI
Project-URL: Coverage: codecov, https://codecov.io/github/aio-libs/aiohttp
Project-URL: Docs: Changelog, https://docs.aiohttp.org/en/stable/changes.html
Project-URL: Docs: RTD, https://docs.aiohttp.org
Project-URL: GitHub: issues, https://github.com/aio-libs/aiohttp/issues
Project-URL: GitHub: repo, https://github.com/aio-libs/aiohttp
Platform: UNKNOWN
Classifier: Development Status :: 5 - Production/Stable
Classifier: Framework :: AsyncIO
Classifier: Intended Audience :: Developers
Classifier: License :: OSI Approved :: Apache Software License
Classifier: Operating System :: POSIX
Classifier: Operating System :: MacOS :: MacOS X
Classifier: Operating System :: Microsoft :: Windows
Classifier: Programming Language :: Python
Classifier: Programming Language :: Python :: 3
Classifier: Programming Language :: Python :: 3.8
Classifier: Programming Language :: Python :: 3.9
Classifier: Programming Language :: Python :: 3.10
Classifier: Programming Language :: Python :: 3.11
Classifier: Programming Language :: Python :: 3.12
Classifier: Topic :: Internet :: WWW/HTTP
Requires-Python: >=3.8
Provides-Extra: speedups
